xiaobaiauto2/__init__.py
xiaobaiauto2/__version__.py
xiaobaiauto2/xiaobaiauto2.py
xiaobaiauto2/config/__init__.py
xiaobaiauto2/config/config.py
xiaobaiauto2/core/__init__.py
xiaobaiauto2/core/core.py
xiaobaiauto2/core/utils.py
xiaobaiauto2/data/GLO_VARS.py
xiaobaiauto2/data/__init__.py
xiaobaiauto2/data/favicon.ico
xiaobaiauto2/data/xiaobaiauto2.db
xiaobaiauto2/test/__init__.py
xiaobaiauto2/test/runTestCase.bat
xiaobaiauto2/test/ApiTest/__init__.py
xiaobaiauto2/test/ApiTest/myMockServer.py
xiaobaiauto2/test/ApiTest/test_allure_report_demo.py
xiaobaiauto2/test/ApiTest/test_cases.py
xiaobaiauto2/test/ApiTest/yewua.py
xiaobaiauto2/test/ApiTest/yewub.py
xiaobaiauto2/test/AppTest/__init__.py
xiaobaiauto2/test/AppTest/conftest.py
xiaobaiauto2/test/AppTest/test_Manzhai_APP_Case1.py
xiaobaiauto2/test/AppTest/test_Manzhai_APP_Case2.py
xiaobaiauto2/test/WebTest/__init__.py
xiaobaiauto2/test/WebTest/conftest.py
xiaobaiauto2/test/WebTest/test_WebUI.py
xiaobaiauto2/testCase_template/__init__.py
xiaobaiauto2/testCase_template/test01.py
xiaobaiauto2/testCase_template/test02.py
xiaobaiauto2/testCase_template/test03.py
xiaobaiauto2/utils/__init__.py
xiaobaiauto2/utils/code_template.py
xiaobaiauto2/utils/help_ui.py
xiaobaiauto2/utils/jmeter_script_template.py
xiaobaiauto2/utils/xiaobaiauto2App.py
xiaobaiauto2/utils/xiaobaiauto2Downloader.py
xiaobaiauto2/utils/xiaobaiauto2Downloader2.py
xiaobaiauto2/utils/xiaobaiauto2Email.py
xiaobaiauto2/utils/xiaobaiauto2Help.py
xiaobaiauto2/utils/xiaobaiauto2Installer.py
xiaobaiauto2/utils/xiaobaiauto2Proxy.py
xiaobaiauto2/utils/xiaobaiauto2Subprocess.py
xiaobaiauto2/utils/xiaobaiauto2Timer.py
xiaobaiauto2/utils/xiaobaiauto2Tools.py
xiaobaiauto2/utils/xiaobaiauto2db.py
xiaobaiauto2/utils/adb/AdbWinApi.dll
xiaobaiauto2/utils/adb/AdbWinUsbApi.dll
xiaobaiauto2/utils/adb/adb.exe
xiaobaiauto2-1.0.1.dist-info/LICENSE
xiaobaiauto2-1.0.1.dist-info/METADATA
xiaobaiauto2-1.0.1.dist-info/WHEEL
xiaobaiauto2-1.0.1.dist-info/entry_points.txt
xiaobaiauto2-1.0.1.dist-info/top_level.txt
xiaobaiauto2-1.0.1.dist-info/RECORD
