Metadata-Version: 2.1
Name: xiaobaiauto2
Version: 1.0.1
Summary: xiaobaiauto2是对自动化框架的第三次更新，功能覆盖UI自动化与API自动化意在帮助对自动化有更多需求且过多时间写代码的人群，让大家的时间花在业务的实现上
Home-page: https://gitee.com/xiaobaiOTS/xiaobaiauto2
Author: xiaobaiTser
Author-email: 807447312@qq.com
Keywords: test auto automation xiaobai xiaobaiauto2 test framework
Classifier: Programming Language :: Python :: 3.7
Classifier: Programming Language :: Python :: 3.8
Classifier: Programming Language :: Python :: 3.9
Classifier: Programming Language :: Python :: 3.10
Classifier: Programming Language :: Python :: 3.11
Classifier: Programming Language :: Python :: 3.12
Classifier: License :: OSI Approved :: Apache Software License
Classifier: Operating System :: OS Independent
Requires-Python: >=3.7
License-File: LICENSE
Provides-Extra: dev
Requires-Dist: pytest; extra == "dev"
Requires-Dist: pytest-cov; extra == "dev"
Requires-Dist: pytest-sugar; extra == "dev"
Requires-Dist: pytest-html; extra == "dev"
Requires-Dist: pytest-ordering; extra == "dev"
Requires-Dist: pytest-rerunfailures; extra == "dev"
Requires-Dist: pytest-xdist; extra == "dev"
Requires-Dist: pytest-instafail; extra == "dev"
Requires-Dist: allure-pytest; extra == "dev"
Provides-Extra: all
Requires-Dist: pytest; extra == "all"
Requires-Dist: pytest-cov; extra == "all"
Requires-Dist: pytest-sugar; extra == "all"
Requires-Dist: pytest-html; extra == "all"
Requires-Dist: pytest-ordering; extra == "all"
Requires-Dist: pytest-rerunfailures; extra == "all"
Requires-Dist: pytest-xdist; extra == "all"
Requires-Dist: pytest-instafail; extra == "all"
Requires-Dist: pyyaml; extra == "all"
Requires-Dist: requests; extra == "all"
Requires-Dist: selenium; extra == "all"
Requires-Dist: allure-pytest; extra == "all"
Requires-Dist: Appium-Python-Client; extra == "all"
Requires-Dist: jmespath; extra == "all"
Requires-Dist: mitmproxy; extra == "all"
